borsh/__init__.py
borsh-0.0.1.dist-info/LICENSE
borsh-0.0.1.dist-info/METADATA
borsh-0.0.1.dist-info/WHEEL
borsh-0.0.1.dist-info/top_level.txt
borsh-0.0.1.dist-info/RECORD
